pladder_client/__init__.py
pladder_client/client.py
pladder_client-0.1.0.dist-info/entry_points.txt
pladder_client-0.1.0.dist-info/WHEEL
pladder_client-0.1.0.dist-info/METADATA
pladder_client-0.1.0.dist-info/RECORD
